chant21/__init__.py
chant21/_version.py
chant21/chant.py
chant21/chson.py
chant21/converterCHSON.py
chant21/converterGABC.py
chant21/parserGABC.py
chant21/volpyano.py
chant21/volpyano_parser.py
chant21/cantus/__init__.py
chant21/cantus/cantus_text.peg
chant21/cantus/cantus_volpiano.peg
chant21/cantus/cltk_syllabifier.py
chant21/cantus/converter.py
chant21/cantus/parser_text.py
chant21/cantus/parser_volpiano.py
chant21/cantus/syllabifier-exceptions.yml
chant21/cantus/syllabifier.py
chant21/examples/__init__.py
chant21/examples/ab_ortu_solis.gabc
chant21/examples/an--salve_regina_simple_tone--solesmes.gabc
chant21/examples/cantus-volpiano-examples.csv
chant21/examples/hy--ut_queant_laxis--solesmes.gabc
chant21/examples/ky--kyrie_ad_lib_x_-_orbis_factor--solesmes.gabc
chant21/examples/kyrie.gabc
chant21/examples/minimal.gabc
chant21/examples/populus_sion.gabc
chant21/examples/salve_regina.gabc
chant21/examples/tr--ab_ortu_solis--solesmes.gabc
chant21/examples/ut_queant_laxis.gabc
chant21/gabc/__init__.py
chant21/gabc/converter.py
chant21/gabc/gabc.peg
chant21/gabc/parser.py
chant21/html/__init__.py
chant21/html/chant.html
chant21/html/displayOptions.html
chant21/html/file.html
chant21/html/widget.html
chant21-0.4.6.dist-info/LICENSE
chant21-0.4.6.dist-info/METADATA
chant21-0.4.6.dist-info/WHEEL
chant21-0.4.6.dist-info/top_level.txt
chant21-0.4.6.dist-info/RECORD
